README.rst
setup.cfg
setup.py
mutalyzer_crossmapper/__init__.py
mutalyzer_crossmapper/crossmapper.py
mutalyzer_crossmapper/location.py
mutalyzer_crossmapper/locus.py
mutalyzer_crossmapper/multi_locus.py
mutalyzer_crossmapper.egg-info/PKG-INFO
mutalyzer_crossmapper.egg-info/SOURCES.txt
mutalyzer_crossmapper.egg-info/dependency_links.txt
mutalyzer_crossmapper.egg-info/requires.txt
mutalyzer_crossmapper.egg-info/top_level.txt