Metadata-Version: 2.1
Name: mutalyzer-crossmapper
Version: 2.0.1
Summary: Mutalyzer HGVS position crossmapper.
Home-page: https://github.com/mutalyzer/crossmapper
Author: Jeroen F.J. Laros
Author-email: J.F.J.Laros@lumc.nl
License: MIT
Keywords: Mutalyzer,HGVS,position,crossmap,convert
Platform: UNKNOWN
Classifier: Intended Audience :: Science/Research
Classifier: Intended Audience :: Developers
Classifier: Operating System :: OS Independent
Classifier: Programming Language :: Python :: 3
Classifier: Topic :: Scientific/Engineering
Provides-Extra: tests
